langchain_chinese/.pypirc
langchain_chinese/__init__.py
langchain_chinese/__version__.py
langchain_chinese/agents/__init__.py
langchain_chinese/agents/base.py
langchain_chinese/agents/prompt.py
langchain_chinese/document_loaders/__init__.py
langchain_chinese/document_loaders/base.py
langchain_chinese/langgraph/__init__.py
langchain_chinese/langgraph/tools_calling.py
langchain_chinese/memory/__init__.py
langchain_chinese/memory/base.py
langchain_chinese/memory/history.py
langchain_chinese/memory/memory_manager.py
langchain_chinese/retrievers/__init__.py
langchain_chinese/retrievers/base.py
langchain_chinese/writing/__init__.py
langchain_chinese/writing/base.py
langchain_chinese/writing/content.py
langchain_chinese/writing/prompts/main.py
langchain_chinese/writing/prompts/translate.py
langchain_chinese/writing/reading/__init__.py
langchain_chinese/writing/reading/base.py
langchain_chinese/writing/task.py
langchain_chinese-0.4.1.dist-info/LICENSE
langchain_chinese-0.4.1.dist-info/METADATA
langchain_chinese-0.4.1.dist-info/WHEEL
langchain_chinese-0.4.1.dist-info/RECORD
