Metadata-Version: 2.1
Name: langchain_chinese
Version: 0.4.1
Summary: Prepare some firendly tool for Chinese LLMs and langchain
Home-page: https://github.com/arcstep/langchain_chinese
License: MIT
Author: arcstep
Author-email: 43801@qq.com
Requires-Python: >=3.9,<3.12
Classifier: License :: OSI Approved :: MIT License
Classifier: Programming Language :: Python :: 3
Classifier: Programming Language :: Python :: 3.9
Classifier: Programming Language :: Python :: 3.10
Classifier: Programming Language :: Python :: 3.11
Requires-Dist: asyncio (>=3.4.3,<4.0.0)
Requires-Dist: langchain (>=0.1.10,<0.2.0)
Requires-Dist: langchain-community (>=0.0.25,<0.0.26)
Requires-Dist: pydantic (>=1,<3)
Requires-Dist: python-dotenv (>=1.0.1,<2.0.0)
Project-URL: Repository, https://github.com/arcstep/langchain_chinese.git
